pip_deepfreeze/__init__.py
pip_deepfreeze/__main__.py
pip_deepfreeze/compat.py
pip_deepfreeze/env-info-json.py
pip_deepfreeze/fixup-vcs-direct-urls.py
pip_deepfreeze/installed_dist.py
pip_deepfreeze/list_installed_depends.py
pip_deepfreeze/pip-list-json.py
pip_deepfreeze/pip.py
pip_deepfreeze/project_name.py
pip_deepfreeze/pyproject_toml.py
pip_deepfreeze/req_file_parser.py
pip_deepfreeze/req_merge.py
pip_deepfreeze/req_parser.py
pip_deepfreeze/sanity.py
pip_deepfreeze/sync.py
pip_deepfreeze/tree.py
pip_deepfreeze/utils.py
pip_deepfreeze-3.1.dist-info/METADATA
pip_deepfreeze-3.1.dist-info/WHEEL
pip_deepfreeze-3.1.dist-info/entry_points.txt
pip_deepfreeze-3.1.dist-info/licenses/LICENSE.txt
pip_deepfreeze-3.1.dist-info/RECORD
