Metadata-Version: 2.4
Name: pip-deepfreeze
Version: 3.1
Summary: A simple pip freeze workflow for Python application developers.
Project-URL: Source, https://github.com/sbidoul/pip-deepfreeze/
Project-URL: Bug Reports, https://github.com/sbidoul/pip-deepfreeze/issues
Project-URL: Changelog, https://github.com/sbidoul/pip-deepfreeze/blob/master/CHANGELOG.md
Author-email: Stéphane Bidoul <stephane.bidoul@gmail.com>
License-Expression: MIT
License-File: LICENSE.txt
Classifier: Development Status :: 5 - Production/Stable
Classifier: Intended Audience :: Developers
Classifier: License :: OSI Approved :: MIT License
Classifier: Programming Language :: Python :: 2
Classifier: Programming Language :: Python :: 2.7
Classifier: Programming Language :: Python :: 3
Classifier: Programming Language :: Python :: 3.6
Classifier: Programming Language :: Python :: 3.7
Classifier: Programming Language :: Python :: 3.8
Classifier: Programming Language :: Python :: 3.9
Classifier: Programming Language :: Python :: 3.10
Classifier: Programming Language :: Python :: 3.11
Classifier: Programming Language :: Python :: 3.12
Classifier: Programming Language :: Python :: 3.13
Classifier: Topic :: Software Development :: Build Tools
Requires-Python: >=3.10
Requires-Dist: click>=8.2
Requires-Dist: httpx
Requires-Dist: packaging>=23
Requires-Dist: pip>=22.2
Requires-Dist: tomli; python_version < '3.11'
Requires-Dist: typer>=0.12.1
Provides-Extra: mypy
Requires-Dist: mypy; extra == 'mypy'
Requires-Dist: types-setuptools; extra == 'mypy'
Requires-Dist: types-toml; extra == 'mypy'
Provides-Extra: test
Requires-Dist: pytest; extra == 'test'
Requires-Dist: pytest-cov; extra == 'test'
Requires-Dist: pytest-xdist; extra == 'test'
Requires-Dist: setuptools; extra == 'test'
Requires-Dist: virtualenv; extra == 'test'
Requires-Dist: wheel; extra == 'test'
Provides-Extra: uv
Requires-Dist: uv>=0.4.10; extra == 'uv'
